glomtf/__init__.py
glomtf/consensus_attention.py
glomtf/glom.py
glomtf/grouped_feed_forward.py
glomtf/pairwisedist.py
glomtf/version.py
glom_tf-0.1.1.dist-info/LICENSE
glom_tf-0.1.1.dist-info/METADATA
glom_tf-0.1.1.dist-info/WHEEL
glom_tf-0.1.1.dist-info/top_level.txt
glom_tf-0.1.1.dist-info/RECORD
